Metadata-Version: 2.1
Name: foolproof
Version: 0.1.8
Summary: Find all exceptions that your code and its dependencies can raise, to make your work foolproof!
Home-page: https://github.com/NicolasMICAUX/foolproof
Author: Nicolas Micaux
Author-email: micaux.nicolas@gmail.com
License: UNKNOWN
Keywords: exception,foolproof
Platform: UNKNOWN
Classifier: Development Status :: 3 - Alpha
Classifier: Intended Audience :: Developers
Classifier: Natural Language :: English
Classifier: Topic :: Utilities
Classifier: Programming Language :: Python :: 3
Classifier: Programming Language :: Python :: 3.5
Classifier: Programming Language :: Python :: 3.6
Classifier: Programming Language :: Python :: 3.7
Classifier: Programming Language :: Python :: 3.8
Classifier: Programming Language :: Python :: 3.9
Classifier: Programming Language :: Python :: 3.10
Classifier: Programming Language :: Python :: 3.11
Requires-Python: >=3.5
